insta_package/Insta_Follower_Scraper.py
insta_package/__init__.py
insta_package/insta_AutoLogin.py
insta_package/insta_Auto_DM.py
insta_package/insta_dm_spammer.py
insta_package/insta_following_scraper.py
insta_package/insta_parser.py
insta_pkg-1.2.0.2.dist-info/LICENSE.txt
insta_pkg-1.2.0.2.dist-info/METADATA
insta_pkg-1.2.0.2.dist-info/WHEEL
insta_pkg-1.2.0.2.dist-info/top_level.txt
insta_pkg-1.2.0.2.dist-info/RECORD
