Metadata-Version: 2.1
Name: insta-pkg
Version: 1.2.0.2
Summary: Instagram Multiple Package
Home-page: https://github.com/WhiteHole00
Author: WhiteHole
Author-email: wlstn7791@gmail.com
License: MIT
Platform: UNKNOWN
Requires-Python: >=3
License-File: LICENSE.txt
